textual_simple_auth/__init__.py
textual_simple_auth/auth.py
textual_simple_auth/decorators.py
textual_simple_auth/demo.py
textual_simple_auth/demo.tcss
textual_simple_auth/login.py
textual_simple_auth/login.tcss
textual_simple_auth-0.3.0.dist-info/LICENSE
textual_simple_auth-0.3.0.dist-info/METADATA
textual_simple_auth-0.3.0.dist-info/WHEEL
textual_simple_auth-0.3.0.dist-info/RECORD
