Metadata-Version: 2.1
Name: textual-simple-auth
Version: 0.3.0
Summary: Simple authentication for Textual apps.
License: MIT
Author: David Fokkema
Author-email: davidfokkema@icloud.com
Requires-Python: >=3.10,<4.0
Classifier: Development Status :: 4 - Beta
Classifier: Environment :: Console
Classifier: Intended Audience :: Developers
Classifier: License :: OSI Approved :: MIT License
Classifier: Operating System :: MacOS
Classifier: Operating System :: Microsoft :: Windows
Classifier: Operating System :: POSIX
Classifier: Programming Language :: Python
Classifier: Programming Language :: Python :: 3
Classifier: Programming Language :: Python :: 3.10
Classifier: Programming Language :: Python :: 3.11
Classifier: Programming Language :: Python :: 3.12
Requires-Dist: click (>=8.1.7,<9.0.0)
Requires-Dist: platformdirs (>=4.2.2,<5.0.0)
Requires-Dist: textual (>=0.67.1,<0.68.0)
